garth_mcp.py
garth_mcp-0.0.2.dist-info/METADATA
garth_mcp-0.0.2.dist-info/WHEEL
garth_mcp-0.0.2.dist-info/entry_points.txt
garth_mcp-0.0.2.dist-info/RECORD
