Metadata-Version: 2.4
Name: garth-mcp
Version: 0.0.2
Summary: Garmin Connect MCP server
Author-email: Matin Tamizi <mtamizi@duck.com>
License: MIT
Keywords: garmin,garmin connect,mcp
Classifier: Development Status :: 3 - Alpha
Classifier: License :: OSI Approved :: MIT License
Classifier: Programming Language :: Python :: 3.13
Requires-Python: >=3.13
Requires-Dist: garth<0.6.0,>=0.5.7
Requires-Dist: mcp<2.0.0,>=1.9.0
